wg_api/__init__.py
wg_api/tanks_list_wot_blitz.py
wg_api-0.0.1.dist-info/LICENSE.txt
wg_api-0.0.1.dist-info/METADATA
wg_api-0.0.1.dist-info/WHEEL
wg_api-0.0.1.dist-info/top_level.txt
wg_api-0.0.1.dist-info/RECORD
