Metadata-Version: 2.1
Name: wg-api
Version: 0.0.1
Summary: wargaming api package
Home-page: https://github.com/encrypted-pig/in_dev_wg
Author: Encoded_pig
Author-email: takonok.3000@ya.ru
License: UNKNOWN
Platform: UNKNOWN
Classifier: Programming Language :: Python :: 3
Classifier: License :: OSI Approved :: MIT License
Classifier: Operating System :: OS Independent
Requires-Python: >=3.6
Requires-Dist: requests
